pypi_pip_template/__init__.py
pypi_pip_template/__main__.py
pypi_pip_template/gui/__init__.py
pypi_pip_template/gui/main.py
pypi_pip_template/utils/__init__.py
pypi_pip_template-0.0.8.dist-info/LICENSE
pypi_pip_template-0.0.8.dist-info/METADATA
pypi_pip_template-0.0.8.dist-info/WHEEL
pypi_pip_template-0.0.8.dist-info/entry_points.txt
pypi_pip_template-0.0.8.dist-info/top_level.txt
pypi_pip_template-0.0.8.dist-info/RECORD
