Metadata-Version: 2.1
Name: pypi-pip-template
Version: 0.0.8
Summary: 
Home-page: 
Author: 
Author-email: 
License: 
Keywords: pypi,pip,template
Classifier: License :: OSI Approved :: MIT License
Classifier: Programming Language :: Python :: 3.8
Classifier: Programming Language :: Python :: 3.9
Classifier: Programming Language :: Python :: 3.10
Classifier: Programming Language :: Python :: 3.11
License-File: LICENSE
